<annotation>
  <folder>VOC2007</folder>
  <filename>/home/skyarrow/Workspace/Drillbit-Detection/Preprocessing/data</filename>
  <source>
    <annotation>PASCAL VOC2007</annotation>
    <database>Unknown</database>
    <image>flickr</image>
    <flickrid>35435</flickrid>
  </source>
  <size>
    <width>640</width>
    <height>640</height>
    <depth>3</depth>
  </size>
  <object>
    <name>0</name>
    <bndbox>
      <xmin>620.0001120000002</xmin>
      <ymin>14.997933999999987</ymin>
      <xmax>662.001456</xmax>
      <ymax>57.99865799999998</ymax>
    </bndbox>
  </object>
  <object>
    <name>0</name>
    <bndbox>
      <xmin>601.003596</xmin>
      <ymin>-23.0001299999999</ymin>
      <xmax>642.0014760000004</xmax>
      <ymax>17.99953000000005</ymax>
    </bndbox>
  </object>
  <object>
    <name>0</name>
    <bndbox>
      <xmin>594.999444</xmin>
      <ymin>53.99837600000001</ymin>
      <xmax>635.9973240000004</xmax>
      <ymax>95.99856799999998</ymax>
    </bndbox>
  </object>
  <object>
    <name>0</name>
    <bndbox>
      <xmin>621.0008040000002</xmin>
      <ymin>94.00119600000016</ymin>
      <xmax>661.0007639999999</xmax>
      <ymax>136.00138800000013</ymax>
    </bndbox>
  </object>
  <object>
    <name>0</name>
    <bndbox>
      <xmin>597.0008280000002</xmin>
      <ymin>132.99979200000007</ymin>
      <xmax>637.9987080000001</xmax>
      <ymax>172.99892</ymax>
    </bndbox>
  </object>
  <object>
    <name>0</name>
    <bndbox>
      <xmin>576.0029279999999</xmin>
      <ymin>11.998184000000037</ymin>
      <xmax>619.0021919999999</xmax>
      <ymax>53.99837600000046</ymax>
    </bndbox>
  </object>
  <object>
    <name>0</name>
    <bndbox>
      <xmin>554.0015640000001</xmin>
      <ymin>49.001254000000245</ymin>
      <xmax>594.0015239999998</xmax>
      <ymax>92.00197800000024</ymax>
    </bndbox>
  </object>
  <object>
    <name>0</name>
    <bndbox>
      <xmin>575.9973839999998</xmin>
      <ymin>92.00197800000024</ymin>
      <xmax>617.998728</xmax>
      <ymax>133.00163799999973</ymax>
    </bndbox>
  </object>
  <object>
    <name>0</name>
    <bndbox>
      <xmin>508.0002239999999</xmin>
      <ymin>-20.000380000000405</ymin>
      <xmax>550.9994879999999</xmax>
      <ymax>21.99981200000002</ymax>
    </bndbox>
  </object>
  <object>
    <name>0</name>
    <bndbox>
      <xmin>527.0022839999997</xmin>
      <ymin>27.00062600000001</ymin>
      <xmax>573.0008519999997</xmax>
      <ymax>70.00135</ymax>
    </bndbox>
  </object>
  <object>
    <name>0</name>
    <bndbox>
      <xmin>614.9994240000001</xmin>
      <ymin>182.99870199999987</ymin>
      <xmax>662.9993760000002</xmax>
      <ymax>228.0004899999999</ymax>
    </bndbox>
  </object>
</annotation>
