<annotation>
  <folder>VOC2007</folder>
  <filename>/home/skyarrow/Workspace/Drillbit-Detection/Preprocessing/data</filename>
  <source>
    <annotation>PASCAL VOC2007</annotation>
    <database>Unknown</database>
    <image>flickr</image>
    <flickrid>35435</flickrid>
  </source>
  <size>
    <width>640</width>
    <height>640</height>
    <depth>3</depth>
  </size>
  <object>
    <name>0</name>
    <bndbox>
      <xmin>68.99999600000001</xmin>
      <ymin>617.001446</ymin>
      <xmax>108.99995600000011</xmax>
      <ymax>660.00217</ymax>
    </bndbox>
  </object>
  <object>
    <name>0</name>
    <bndbox>
      <xmin>-4.998544000000038</xmin>
      <ymin>538.9987160000001</ymin>
      <xmax>37.00280000000021</xmax>
      <ymax>580.9989080000003</ymax>
    </bndbox>
  </object>
  <object>
    <name>0</name>
    <bndbox>
      <xmin>108.99995600000011</xmin>
      <ymin>609.999568</ymin>
      <xmax>153.0026840000005</xmax>
      <ymax>654.000824</ymax>
    </bndbox>
  </object>
  <object>
    <name>2</name>
    <bndbox>
      <xmin>-4.998544000000038</xmin>
      <ymin>609.999568</ymin>
      <xmax>37.00280000000021</xmax>
      <ymax>649.9986960000001</ymax>
    </bndbox>
  </object>
  <object>
    <name>2</name>
    <bndbox>
      <xmin>30.00072799999998</xmin>
      <ymin>573.9988759999999</ymin>
      <xmax>77.00275999999985</xmax>
      <ymax>620.998036</ymax>
    </bndbox>
  </object>
  <object>
    <name>2</name>
    <bndbox>
      <xmin>82.99859599999945</xmin>
      <ymin>544.9982160000002</ymin>
      <xmax>123.9964759999998</xmax>
      <ymax>593.9984399999998</ymax>
    </bndbox>
  </object>
  <object>
    <name>2</name>
    <bndbox>
      <xmin>140.9999240000002</xmin>
      <ymin>582.0012859999999</ymin>
      <xmax>180.0019639999996</xmax>
      <ymax>630.000978</ymax>
    </bndbox>
  </object>
  <object>
    <name>2</name>
    <bndbox>
      <xmin>183.00126800000044</xmin>
      <ymin>595.9995039999999</ymin>
      <xmax>222.00330799999983</xmax>
      <ymax>642.998664</ymax>
    </bndbox>
  </object>
  <object>
    <name>2</name>
    <bndbox>
      <xmin>223.99914799999988</xmin>
      <ymin>601.999004</ymin>
      <xmax>274.0004840000006</xmax>
      <ymax>639.0002279999999</ymax>
    </bndbox>
  </object>
</annotation>
