<annotation>
  <folder>VOC2007</folder>
  <filename>/home/skyarrow/Workspace/Drillbit-Detection/Preprocessing/data</filename>
  <source>
    <annotation>PASCAL VOC2007</annotation>
    <database>Unknown</database>
    <image>flickr</image>
    <flickrid>35435</flickrid>
  </source>
  <size>
    <width>640</width>
    <height>640</height>
    <depth>3</depth>
  </size>
  <object>
    <name>2</name>
    <bndbox>
      <xmin>5.120956000000206</xmin>
      <ymin>298.54247599999997</ymin>
      <xmax>140.43336399999998</xmax>
      <ymax>420.851052</ymax>
    </bndbox>
  </object>
  <object>
    <name>2</name>
    <bndbox>
      <xmin>130.50405999999998</xmin>
      <ymin>297.00660400000004</ymin>
      <xmax>246.14635599999974</xmax>
      <ymax>407.00605199999995</ymax>
    </bndbox>
  </object>
  <object>
    <name>2</name>
    <bndbox>
      <xmin>235.88995599999976</xmin>
      <ymin>300.08204</ymin>
      <xmax>366.14623600000004</xmax>
      <ymax>413.1606159999999</ymax>
    </bndbox>
  </object>
  <object>
    <name>2</name>
    <bndbox>
      <xmin>347.42969200000016</xmin>
      <ymin>290.080412</ymin>
      <xmax>482.5757800000001</xmax>
      <ymax>413.1569239999999</ymax>
    </bndbox>
  </object>
  <object>
    <name>2</name>
    <bndbox>
      <xmin>456.66035200000033</xmin>
      <ymin>280.08247599999993</ymin>
      <xmax>598.2873759999998</xmax>
      <ymax>407.00605200000007</ymax>
    </bndbox>
  </object>
  <object>
    <name>2</name>
    <bndbox>
      <xmin>578.9637640000001</xmin>
      <ymin>299.31225799999993</ymin>
      <xmax>703.2879640000001</xmax>
      <ymax>420.0812699999999</ymax>
    </bndbox>
  </object>
  <object>
    <name>2</name>
    <bndbox>
      <xmin>290.08810000000017</xmin>
      <ymin>589.579144</ymin>
      <xmax>413.935516</xmax>
      <ymax>713.4235920000001</ymax>
    </bndbox>
  </object>
  <object>
    <name>2</name>
    <bndbox>
      <xmin>400.0893759999999</xmin>
      <ymin>587.2679519999999</ymin>
      <xmax>520.859872</xmax>
      <ymax>688.8053360000001</ymax>
    </bndbox>
  </object>
  <object>
    <name>2</name>
    <bndbox>
      <xmin>470.85576400000036</xmin>
      <ymin>485.72872200000006</ymin>
      <xmax>598.5507160000002</xmax>
      <ymax>605.7297980000001</ymax>
    </bndbox>
  </object>
  <object>
    <name>2</name>
    <bndbox>
      <xmin>352.3943439999998</xmin>
      <ymin>509.57719599999996</ymin>
      <xmax>475.4711440000001</xmax>
      <ymax>602.6525159999999</ymax>
    </bndbox>
  </object>
  <object>
    <name>2</name>
    <bndbox>
      <xmin>227.01123999999982</xmin>
      <ymin>507.26784999999995</ymin>
      <xmax>356.24188000000004</xmax>
      <ymax>604.9618619999999</ymax>
    </bndbox>
  </object>
  <object>
    <name>2</name>
    <bndbox>
      <xmin>132.3917919999999</xmin>
      <ymin>488.80785000000003</ymin>
      <xmax>244.70214399999986</xmax>
      <ymax>610.344798</ymax>
    </bndbox>
  </object>
  <object>
    <name>2</name>
    <bndbox>
      <xmin>14.703759999999647</xmin>
      <ymin>502.65285000000006</ymin>
      <xmax>143.9344000000001</xmax>
      <ymax>619.5747980000001</ymax>
    </bndbox>
  </object>
  <object>
    <name>2</name>
    <bndbox>
      <xmin>-35.297575999999935</xmin>
      <ymin>411.88503000000003</ymin>
      <xmax>73.16524000000027</xmax>
      <ymax>523.424042</ymax>
    </bndbox>
  </object>
  <object>
    <name>2</name>
    <bndbox>
      <xmin>57.78063999999995</xmin>
      <ymin>394.19111999999996</ymin>
      <xmax>184.704976</xmax>
      <ymax>495.72850400000004</ymax>
    </bndbox>
  </object>
  <object>
    <name>2</name>
    <bndbox>
      <xmin>163.93437999999992</xmin>
      <ymin>401.1154660000001</ymin>
      <xmax>310.09085200000004</xmax>
      <ymax>521.1165420000001</ymax>
    </bndbox>
  </object>
  <object>
    <name>2</name>
    <bndbox>
      <xmin>293.16779199999996</xmin>
      <ymin>394.19112000000007</ymin>
      <xmax>406.24321599999985</xmax>
      <ymax>516.499696</ymax>
    </bndbox>
  </object>
  <object>
    <name>2</name>
    <bndbox>
      <xmin>397.7802999999999</xmin>
      <ymin>407.27003</ymin>
      <xmax>525.4752519999997</xmax>
      <ymax>528.039042</ymax>
    </bndbox>
  </object>
  <object>
    <name>2</name>
    <bndbox>
      <xmin>518.550796</xmin>
      <ymin>400.3456839999999</ymin>
      <xmax>654.705892</xmax>
      <ymax>518.03926</ymax>
    </bndbox>
  </object>
</annotation>
